{
  "openapi": "3.0.0",
  "info": {
    "title": "Fagord API",
    "description": "Åpent API for deg som ønsker å jobbe med fagtermer",
    "version": "1.0.0"
  },
  "servers": [
    null
  ],
  "tags": [
    "Artikler",
    "Fagfelt",
    "Termer"
  ],
  "paths": {
    "/api/termer/": {
      "get": {
        "tags": [
          "Termer"
        ],
        "description": "",
        "responses": {
          "200": {
            "description": "OK",
            "content": {
              "application/json": {
                "schema": {
                  "$ref": "#/components/schemas/Term"
                }
              },
              "application/xml": {
                "schema": {
                  "$ref": "#/components/schemas/Term"
                }
              }
            }
          }
        }
      },
      "post": {
        "tags": [
          "Termer"
        ],
        "description": "",
        "responses": {
          "200": {
            "description": "OK"
          }
        },
        "requestBody": {
          "content": {
            "application/json": {
              "schema": {
                "type": "object",
                "properties": {
                  "en": {
                    "example": "any"
                  },
                  "pos": {
                    "example": "any"
                  }
                }
              }
            }
          }
        }
      }
    },
    "/api/termer/{termId}": {
      "get": {
        "tags": [
          "Termer"
        ],
        "description": "",
        "parameters": [
          {
            "name": "termId",
            "in": "path",
            "required": true,
            "schema": {
              "type": "string"
            }
          }
        ],
        "responses": {
          "200": {
            "description": "OK"
          }
        }
      },
      "put": {
        "tags": [
          "Termer"
        ],
        "description": "",
        "parameters": [
          {
            "name": "termId",
            "in": "path",
            "required": true,
            "schema": {
              "type": "string"
            }
          }
        ],
        "responses": {
          "200": {
            "description": "OK"
          }
        }
      },
      "delete": {
        "tags": [
          "Termer"
        ],
        "description": "",
        "parameters": [
          {
            "name": "termId",
            "in": "path",
            "required": true,
            "schema": {
              "type": "string"
            }
          }
        ],
        "responses": {
          "200": {
            "description": "OK"
          }
        }
      }
    },
    "/api/termer/{termId}/varianter": {
      "get": {
        "tags": [
          "Termer"
        ],
        "description": "",
        "parameters": [
          {
            "name": "termId",
            "in": "path",
            "required": true,
            "schema": {
              "type": "string"
            }
          }
        ],
        "responses": {
          "200": {
            "description": "OK"
          }
        }
      },
      "post": {
        "tags": [
          "Termer"
        ],
        "description": "",
        "parameters": [
          {
            "name": "termId",
            "in": "path",
            "required": true,
            "schema": {
              "type": "string"
            }
          }
        ],
        "responses": {
          "200": {
            "description": "OK"
          }
        }
      },
      "put": {
        "tags": [
          "Termer"
        ],
        "description": "",
        "parameters": [
          {
            "name": "termId",
            "in": "path",
            "required": true,
            "schema": {
              "type": "string"
            }
          }
        ],
        "responses": {
          "200": {
            "description": "OK"
          }
        }
      }
    },
    "/api/fagfelt/": {
      "get": {
        "tags": [
          "Fagfelt"
        ],
        "description": "",
        "responses": {
          "200": {
            "description": "OK"
          }
        }
      }
    },
    "/api/artikler/": {
      "get": {
        "tags": [
          "Artikler"
        ],
        "description": "",
        "responses": {
          "200": {
            "description": "OK"
          }
        }
      }
    },
    "/api/artikler/{articleId}": {
      "get": {
        "tags": [
          "Artikler"
        ],
        "description": "",
        "parameters": [
          {
            "name": "articleId",
            "in": "path",
            "required": true,
            "schema": {
              "type": "string"
            }
          }
        ],
        "responses": {
          "200": {
            "description": "OK"
          }
        }
      }
    }
  },
  "components": {
    "schemas": {
      "Variant": {
        "type": "object",
        "properties": {
          "term": {
            "type": "string",
            "example": "overgangsmetall"
          },
          "dialect": {
            "type": "string",
            "example": "nb"
          },
          "votes": {
            "type": "string",
            "example": "3"
          }
        },
        "required": [
          "term",
          "dialect"
        ],
        "xml": {
          "name": "Variant"
        }
      },
      "Term": {
        "type": "object",
        "properties": {
          "_id": {
            "type": "string",
            "example": "transition_metal_1"
          },
          "en": {
            "type": "string",
            "example": "transition metal"
          },
          "nb": {
            "type": "string",
            "example": "overgangsmetall"
          },
          "nn": {
            "type": "string",
            "example": "overgangsmetall"
          },
          "variants": {
            "type": "object",
            "properties": {
              "schema": {
                "xml": {
                  "name": "variant"
                },
                "$ref": "#/components/schemas/Variant"
              }
            }
          },
          "field": {
            "type": "string",
            "example": "Kjemi"
          },
          "subfield": {
            "type": "string",
            "example": "Uorganisk kjemi"
          },
          "pos": {
            "type": "string",
            "example": "Substantiv"
          },
          "reference": {
            "type": "string",
            "example": "https://no.wikipedia.org/wiki/Overgangsmetall"
          },
          "_added": {
            "type": "string",
            "example": "2020-10-07T10:00:00.000Z"
          },
          "_modified": {
            "type": "string",
            "example": "2020-10-07T10:00:00.000Z"
          },
          "_active": {
            "type": "boolean",
            "example": true
          },
          "definition": {
            "type": "string",
            "example": "Metall i d-blokka i periodesystemet"
          }
        },
        "required": [
          "_id",
          "en",
          "pos",
          "_added",
          "_modified",
          "_active"
        ],
        "xml": {
          "name": "Term"
        }
      }
    }
  }
}